{
    "__created_at": 1583961662,
    "__updated_at": 1583961794,
    "data": {
        "uniqueid": "craig-200311152058",
        "utm_source": null,
        "utm_medium": null,
        "utm_campaign": null,
        "gclid": null,
        "visitor_id": null,
        "configUrl": "https://dev2-studio-shed.pantheonsite.io/dc/step-1.php?depth=12&length=20&trim=Cedar%20Plank&sidingColor=Elegant%20Red&doorColor=Fireworks&eaveColor=Timberline%20Brown&metalColor=&floorOption=Vermont%20Maple&bathroomFloorOption=&cabinetColor=&countertopColor=&front=F20-D36L-BL&back=B20-BL&left=L12x-BL&right=R12x-BL&foundation=Foundation&doorStyleKey=full-lite-glass-door&uniqueid=craig-200311152058",
        "imageUrl": "https://idearoom-render.s3.amazonaws.com/studioshedsignature-render/product:475-360:58eb95a4eaf7299251c929dc3ba61159.png",
        "email": null,
        "firstName": null,
        "lastName": null,
        "phone": null,
        "model": "signature",
        "depth": 12,
        "length": 20,
        "area": 240,
        "frontSKU": "F20-D36L-BL",
        "backSKU": "B20-BL",
        "leftSKU": "L12x-BL",
        "rightSKU": "R12x-BL",
        "total": 25146,
        "size": "12' x 20' Base Price",
        "sizePrice": 17286,
        "siding": "Cedar Plank",
        "sidingPrice": 5040,
        "right": "Centered 36\" x 36\" Operable Window",
        "rightPrice": 675,
        "left": "Centered 36\" x 36\" Operable Window",
        "leftPrice": 675,
        "front": "Left Justified 36\" Door",
        "frontPrice": 450,
        "sidingColor": "Elegant Red",
        "sidingColorPrice": 0,
        "doorColor": "Fireworks",
        "doorColorPrice": 300,
        "eavesColor": "Timberline Brown",
        "eavesColorPrice": 1680,
        "accessory": "Full-Lite Glass Door",
        "accessoryPrice": 390,
        "foundation": "",
        "foundationPrice": 0,
        "service": "",
        "servicePrice": 0,
        "shipping": "",
        "shippingPrice": 0
    }
}